oip_mlops_client/__init__.py
oip_mlops_client/lib.py
oip_mlops_client/mlops.py
oip_mlops_client/rest.py
oip_mlops_client/wavfile.py
oip_mlops_client-0.0.5.dist-info/METADATA
oip_mlops_client-0.0.5.dist-info/WHEEL
oip_mlops_client-0.0.5.dist-info/top_level.txt
oip_mlops_client-0.0.5.dist-info/RECORD
