Metadata-Version: 2.1
Name: oip-mlops-client
Version: 0.0.5
Summary: This is the API client of Open Innovation Platform - MLOPS
Home-page: UNKNOWN
Author: Rachid Belmeskine
Author-email: rachid.belmeskine@gmail.com
License: PRIVATE LICENSE
Platform: UNKNOWN
Requires-Python: >=3.7
Requires-Dist: requests
Requires-Dist: pandas
Requires-Dist: typing
Requires-Dist: mlflow
Requires-Dist: numpy
Requires-Dist: Pillow
Requires-Dist: matplotlib
Requires-Dist: plotly
